quantum_anomaly_detection/__init__.py
quantum_anomaly_detection/detector.py
quantum_anomaly_detection-0.2.7.dist-info/METADATA
quantum_anomaly_detection-0.2.7.dist-info/WHEEL
quantum_anomaly_detection-0.2.7.dist-info/top_level.txt
quantum_anomaly_detection-0.2.7.dist-info/RECORD
